[
  {
    "name": "Canon EOS 250D",
    "brand": "Samsung",
    "desc": "Canon DSLR, 24MP sensor, yeni.",
    "price": 2530,
    "old_price": 3666,
    "discount": 31,
    "rating": 4.7,
    "review_count": 13,
    "condition": "yeni",
    "location": "Bakı",
    "image": "images/cameras-1.webp"
  },
  {
    "name": "Nikon D3300",
    "brand": "LG",
    "desc": "İkinci əl Nikon, əla vəziyyətdə.",
    "price": 420,
    "old_price": 677,
    "discount": 38,
    "rating": 4.3,
    "review_count": 9,
    "condition": "islenmis",
    "location": "Gəncə",
    "image": "images/cameras-2.webp"
  },
  {
    "name": "Sony Alpha A6000",
    "brand": "Bosch",
    "desc": "Sony mirrorless, Wi-Fi dəstəyi.",
    "price": 1710,
    "old_price": 2408,
    "discount": 29,
    "rating": 4.6,
    "review_count": 11,
    "condition": "yeni",
    "location": "Sumqayıt",
    "image": "images/cameras-3.webp"
  },
  {
    "name": "Canon PowerShot SX150",
    "brand": "Artel",
    "desc": "Köhnə model, lakin işlək vəziyyətdə.",
    "price": 870,
    "old_price": 1403,
    "discount": 38,
    "rating": 3.9,
    "review_count": 6,
    "condition": "islenmis",
    "location": "Şamaxı",
    "image": "images/cameras-4.webp"
  },
  {
    "name": "GoPro HERO8 Black",
    "brand": "Samsung",
    "desc": "GoPro aksiyon kamerası, suya davamlı.",
    "price": 1980,
    "old_price": 3094,
    "discount": 36,
    "rating": 4.5,
    "review_count": 10,
    "condition": "yeni",
    "location": "Mingəçevir",
    "image": "images/cameras-5.webp"
  },
  {
    "name": "Nikon Z6",
    "brand": "LG",
    "desc": "Nikon Z6, full-frame sensorlu kamera.",
    "price": 3720,
    "old_price": 4960,
    "discount": 25,
    "rating": 4.8,
    "review_count": 14,
    "condition": "yeni",
    "location": "Şəki",
    "image": "images/cameras-6.webp"
  },
  {
    "name": "Canon EOS 1300D",
    "brand": "Bosch",
    "desc": "Canon EOS 1300D, ikinci əl.",
    "price": 530,
    "old_price": 914,
    "discount": 42,
    "rating": 4.2,
    "review_count": 8,
    "condition": "islenmis",
    "location": "Tovuz",
    "image": "images/cameras-7.webp"
  },
  {
    "name": "Sony Cyber-shot W800",
    "brand": "Artel",
    "desc": "Kompakt point-and-shoot kamera.",
    "price": 370,
    "old_price": 552,
    "discount": 33,
    "rating": 4.0,
    "review_count": 5,
    "condition": "islenmis",
    "location": "Quba",
    "image": "images/cameras-8.webp"
  },
  {
    "name": "Canon Vixia HF R800",
    "brand": "Samsung",
    "desc": "FHD çəkiliş, Wi-Fi funksiyası ilə.",
    "price": 1480,
    "old_price": 2145,
    "discount": 31,
    "rating": 4.4,
    "review_count": 9,
    "condition": "yeni",
    "location": "Lənkəran",
    "image": "images/cameras-9.webp"
  },
  {
    "name": "Nikon Coolpix A10",
    "brand": "LG",
    "desc": "Əlverişli və yüngül kamera.",
    "price": 230,
    "old_price": 365,
    "discount": 37,
    "rating": 3.8,
    "review_count": 4,
    "condition": "islenmis",
    "location": "Bərdə",
    "image": "images/cameras-10.webp"
  },
  {
    "name": "Xiaomi Yi 4K Action",
    "brand": "Bosch",
    "desc": "4K aksiyon kamerası, geniş bucaqlı.",
    "price": 2640,
    "old_price": 3826,
    "discount": 31,
    "rating": 4.5,
    "review_count": 10,
    "condition": "yeni",
    "location": "Zaqatala",
    "image": "images/cameras-11.webp"
  },
  {
    "name": "Sony RX100 III",
    "brand": "Artel",
    "desc": "Sony RX100, premium kompaktdır.",
    "price": 2850,
    "old_price": 3958,
    "discount": 28,
    "rating": 4.7,
    "review_count": 13,
    "condition": "yeni",
    "location": "Astara",
    "image": "images/cameras-12.webp"
  },
  {
    "name": "Canon AE-1 Program",
    "brand": "Samsung",
    "desc": "Köhnə analog kamera, vintage stil.",
    "price": 390,
    "old_price": 650,
    "discount": 40,
    "rating": 3.9,
    "review_count": 3,
    "condition": "islenmis",
    "location": "Qazax",
    "image": "images/cameras-13.webp"
  },
  {
    "name": "Sony Alpha A6000",
    "brand": "LG",
    "desc": "Yeni gəlmiş Sony A6000.",
    "price": 1980,
    "old_price": 2712,
    "discount": 27,
    "rating": 4.6,
    "review_count": 12,
    "condition": "yeni",
    "location": "Şəmkir",
    "image": "images/cameras-14.webp"
  },
  {
    "name": "Canon PowerShot SX620",
    "brand": "Bosch",
    "desc": "Canon PowerShot, az istifadə olunub.",
    "price": 760,
    "old_price": 1085,
    "discount": 30,
    "rating": 4.1,
    "review_count": 6,
    "condition": "islenmis",
    "location": "Şirvan",
    "image": "images/cameras-15.webp"
  },
  {
    "name": "Nikon D5200",
    "brand": "Artel",
    "desc": "Nikon D5200, 18-55 obyektiv ilə.",
    "price": 950,
    "old_price": 1338,
    "discount": 29,
    "rating": 4.5,
    "review_count": 10,
    "condition": "yeni",
    "location": "Balakən",
    "image": "images/cameras-16.webp"
  },
  {
    "name": "Fujifilm FinePix S2950",
    "brand": "Samsung",
    "desc": "Əla görüntü, az istifadə olunub.",
    "price": 1190,
    "old_price": 1776,
    "discount": 33,
    "rating": 4.0,
    "review_count": 7,
    "condition": "islenmis",
    "location": "Şəki",
    "image": "images/cameras-17.webp"
  },
  {
    "name": "Panasonic Lumix G7",
    "brand": "LG",
    "desc": "Panasonic Lumix G7, 4K çəkiliş.",
    "price": 2410,
    "old_price": 3394,
    "discount": 29,
    "rating": 4.6,
    "review_count": 11,
    "condition": "yeni",
    "location": "Mingəçevir",
    "image": "images/cameras-18.webp"
  },
  {
    "name": "Polaroid Snap",
    "brand": "Bosch",
    "desc": "Polaroid anlıq şəkil kamerası.",
    "price": 670,
    "old_price": 943,
    "discount": 29,
    "rating": 4.0,
    "review_count": 6,
    "condition": "yeni",
    "location": "Quba",
    "image": "images/cameras-19.webp"
  },
  {
    "name": "Canon EOS M50",
    "brand": "Artel",
    "desc": "Canon M50, vlog üçün ideal seçim.",
    "price": 2950,
    "old_price": 3882,
    "discount": 24,
    "rating": 4.8,
    "review_count": 15,
    "condition": "yeni",
    "location": "Bakı",
    "image": "images/cameras-20.webp"
  }
]
